imgbyte/__init__.py
imgbyte/imgbyte.py
imgbyte-0.1.1.dist-info/METADATA
imgbyte-0.1.1.dist-info/WHEEL
imgbyte-0.1.1.dist-info/top_level.txt
imgbyte-0.1.1.dist-info/RECORD
