Metadata-Version: 2.4
Name: imgbyte
Version: 0.1.1
Summary: Automation library for interacting with Imgflip using Selenium and Requests
Home-page: https://github.com/CreeperKing77/imgbyte
Author: 32-Bit
Classifier: Programming Language :: Python :: 3
Classifier: Operating System :: OS Independent
Requires-Python: >=3.11
Requires-Dist: selenium
Requires-Dist: requests
Dynamic: author
Dynamic: classifier
Dynamic: description
Dynamic: description-content-type
Dynamic: home-page
Dynamic: requires-dist
Dynamic: requires-python
Dynamic: summary
